mySweetCache/__init__.py
mySweetCache/exceptions.py
mySweetCache/mySweetCache.py
mySweetCache/save_helper.py
mySweetCache/setup.py
mySweetCache/utils.py
mysweetcache-1.1.0.dist-info/METADATA
mysweetcache-1.1.0.dist-info/WHEEL
mysweetcache-1.1.0.dist-info/licenses/LICENSE.md
mysweetcache-1.1.0.dist-info/RECORD
