Metadata-Version: 2.1
Name: mySweetCache
Version: 1.1.0
Summary: Package to fast and easy cache
Project-URL: Homepage, https://github.com/chwilko/mySweetCache
Author-email: Bartłomiej Chwiłkowski <bartekchwilkowski@gmail.com>
License-File: LICENSE.md
Classifier: License :: OSI Approved :: MIT License
Classifier: Operating System :: OS Independent
Classifier: Programming Language :: Python :: 3
Requires-Python: >=3.7
